reactpy_apexcharts/__init__.py
reactpy_apexcharts/bundle.dev.js
reactpy_apexcharts/bundle.min.js
reactpy_apexcharts/chart_wrapper.py
reactpy_apexcharts-0.0.12.dist-info/LICENSE
reactpy_apexcharts-0.0.12.dist-info/METADATA
reactpy_apexcharts-0.0.12.dist-info/WHEEL
reactpy_apexcharts-0.0.12.dist-info/RECORD
